langservehub/__init__.py
langservehub/cli.py
package_template/README.md
package_template/package_template/__init__.py
package_template/package_template/chain.py
package_template/poetry.lock
package_template/pyproject.toml
package_template/tests/__init__.py
project_template/README.md
project_template/app/__init__.py
project_template/app/app.py
project_template/app/server.py
project_template/packages/README.md
project_template/poetry.lock
project_template/pyproject.toml
langservehub-0.1.13.dist-info/METADATA
langservehub-0.1.13.dist-info/WHEEL
langservehub-0.1.13.dist-info/entry_points.txt
langservehub-0.1.13.dist-info/RECORD
